DD_Forge/__init__.py
DD_Forge/ai_model_run.py
DD_Forge/app.py
DD_Forge/celery_worker.py
DD_Forge/driver_select.py
DD_Forge/models.py
DD_Forge-0.1.0.dist-info/METADATA
DD_Forge-0.1.0.dist-info/WHEEL
DD_Forge-0.1.0.dist-info/entry_points.txt
DD_Forge-0.1.0.dist-info/top_level.txt
DD_Forge-0.1.0.dist-info/RECORD
